RTL_EYE/spi_slave_debug.v
`timescale 1ns / 1ps

module spi_slave_debug #(
    parameter TOTAL_BYTES = 7'd72 
)(
    input  wire clk,        // Xung nhịp hệ thống của FPGA (VD: 50MHz)
    input  wire rst_n,      // Nút nhấn Reset (Active Low)
    
    // Giao tiếp SPI từ MCU
    input  wire spi_cs,     // Chân Chip Select (Nối với P1.8 của MCU)
    input  wire spi_clk,    // Chân SPI Clock
    input  wire spi_mosi,   // Chân MOSI nhận dữ liệu
    
    // Output Debug
    output wire led_done    // Nối ra 1 con LED trên board FPGA
);

    // =========================================================================
    // 1. MẠCH ĐỒNG BỘ CDC (Chống nhiễu Clock Domain Crossing)
    // =========================================================================
    reg [2:0] cs_sync;
    reg [2:0] sck_sync;
    reg [1:0] mosi_sync;

    always @(posedge clk or negedge rst_n) begin
        if (!rst_n) begin
            cs_sync   <= 3'b111;
            sck_sync  <= 3'b000;
            mosi_sync <= 2'b00;
        end else begin
            // Dịch tín hiệu qua các thanh ghi để đồng bộ với Clock của FPGA
            cs_sync   <= {cs_sync[1:0], spi_cs};
            sck_sync  <= {sck_sync[1:0], spi_clk};
            mosi_sync <= {mosi_sync[0], spi_mosi};
        end
    end

    // Phát hiện các sườn tín hiệu
    wire cs_active  = ~cs_sync[1];             // Đang trong quá trình truyền (CS = 0)
    wire cs_fall    = (cs_sync[2:1] == 2'b10); // Sườn âm CS -> Bắt đầu 1 khung mới
    wire cs_rise    = (cs_sync[2:1] == 2'b01); // Sườn dương CS -> Kết thúc truyền
    wire sck_rise   = (sck_sync[2:1] == 2'b01); // Sườn dương SCK (Dành cho SPI Mode 0)

    // =========================================================================
    // 2. BỘ ĐẾM BIT & BYTE
    // =========================================================================
    reg [2:0] bit_cnt;  // Đếm từ 0 đến 7 (8 bits)
    reg [6:0] byte_cnt; // Đếm số lượng byte nhận được
    reg       led_reg;  // Thanh ghi giữ trạng thái LED

    always @(posedge clk or negedge rst_n) begin
        if (!rst_n) begin
            bit_cnt  <= 3'd0;
            byte_cnt <= 7'd0;
            led_reg  <= 1'b0;
        end else begin
            
            // a. Khi MCU kéo CS xuống để bắt đầu gửi
            if (cs_fall) begin
                bit_cnt  <= 3'd0;
                byte_cnt <= 7'd0;
                led_reg  <= 1'b0; // Tắt đèn LED để chuẩn bị cho lượt test mới
            end 
            
            // b. Đang trong quá trình nhận dữ liệu
            else if (cs_active) begin
                if (sck_rise) begin
                    bit_cnt <= bit_cnt + 1'b1;
                    
                    // Nếu đếm đủ 8 bit -> Tăng biến đếm byte lên 1
                    if (bit_cnt == 3'd7) begin
                        byte_cnt <= byte_cnt + 1'b1;
                    end
                end
            end
            
            // c. Khi MCU kéo CS lên để kết thúc khung truyền
            else if (cs_rise) begin
                // CHỈ BẬT ĐÈN NẾU NHẬN ĐÚNG 72 BYTES
                if (byte_cnt == 7'd72) begin
                    led_reg <= 1'b1;
                end
            end
            
        end
    end

    // Xuất tín hiệu ra chân vật lý
    assign led_done = led_reg;

endmodule

RTL_EYE/tb_spi_slave_debug.v
`timescale 1ns / 1ps

module tb_spi_slave_debug();

    // =========================================================================
    // 1. KHAI BÁO TÍN HIỆU
    // =========================================================================
    reg  clk;
    reg  rst_n;
    reg  spi_cs;
    reg  spi_clk;
    reg  spi_mosi;
    wire led_done;

    integer i; // Biến vòng lặp

    // =========================================================================
    // 2. KHỞI TẠO DUT (Device Under Test) - Kết nối module của bạn
    // =========================================================================
    spi_slave_debug #(
        .TOTAL_BYTES(72)
    ) uut (
        .clk(clk),
        .rst_n(rst_n),
        .spi_cs(spi_cs),
        .spi_clk(spi_clk),
        .spi_mosi(spi_mosi),
        .led_done(led_done)
    );

    // =========================================================================
    // 3. TẠO XUNG NHỊP HỆ THỐNG (50MHz -> Chu kỳ 20ns)
    // =========================================================================
    initial begin
        clk = 0;
        forever #10 clk = ~clk; // Đảo trạng thái mỗi 10ns
    end

    // =========================================================================
    // 4. TASK GỬI 1 BYTE QUA SPI (SPI MODE 0)
    // =========================================================================
    task send_spi_byte;
        input [7:0] data;
        integer bit_idx;
        begin
            // Truyền MSB First (Bit 7 xuống Bit 0)
            for (bit_idx = 7; bit_idx >= 0; bit_idx = bit_idx - 1) begin
                spi_mosi = data[bit_idx]; // Đặt dữ liệu lên dây MOSI
                #40;                      // Đợi dữ liệu ổn định (Setup time)
                
                spi_clk = 1;              // Sườn dương SCK (FPGA sẽ đọc ở đây)
                #40;                      // Giữ SCK mức cao (Hold time)
                
                spi_clk = 0;              // Sườn âm SCK
                #40;                      // Giữ SCK mức thấp
            end
        end
    endtask

    // =========================================================================
    // 5. KỊCH BẢN MÔ PHỎNG (STIMULUS)
    // =========================================================================
    initial begin
        // Khởi tạo ghi file Waveform để xem bằng ModelSim hoặc GTKWave
        $dumpfile("tb_spi_waveform.vcd");
        $dumpvars(0, tb_spi_slave_debug);

        // Khởi tạo các tín hiệu ở trạng thái nghỉ
        rst_n    = 0;
        spi_cs   = 1; // CS nghỉ ở mức 1
        spi_clk  = 0; // SPI Mode 0: Clock nghỉ ở mức 0
        spi_mosi = 0;

        $display("---------------------------------------------------");
        $display("[TIME: %0t ns] BAT DAU KHOI DONG HE THONG", $time);

        // Nhả Reset sau 100ns
        #100 rst_n = 1;
        #100;

        // -----------------------------------------------------------
        // KỊCH BẢN: MCU GỬI ĐÚNG 72 BYTES
        // -----------------------------------------------------------
        $display("[TIME: %0t ns] MCU KEO CS XUONG 0 -> BAT DAU GUI", $time);
        spi_cs = 0; 
        #100; // Đợi một chút sau khi kéo CS

        // Vòng lặp gửi 72 bytes (Tôi gửi giá trị từ 0 đến 71 để dễ nhìn trên Waveform)
        for (i = 0; i < 72; i = i + 1) begin
            send_spi_byte(i);
        end

        // -----------------------------------------------------------
        // KẾT THÚC KHUNG TRUYỀN
        // -----------------------------------------------------------
        #100;
        spi_cs = 1; // MCU kéo CS lên 1 để báo kết thúc (Kích hoạt FSM trên FPGA)
        $display("[TIME: %0t ns] MCU KEO CS LEN 1 -> KET THUC GUI", $time);

        // Đợi một chút để FPGA xử lý logic sườn lên của CS
        #100;

        // -----------------------------------------------------------
        // KIỂM TRA KẾT QUẢ
        // -----------------------------------------------------------
        if (led_done === 1'b1) begin
            $display("=> [PASS] led_done = 1. FPGA da nhan va dem dung 72 bytes!");
        end else begin
            $display("=> [FAIL] led_done = 0. Co loi xay ra trong qua trinh dem!");
        end
        $display("---------------------------------------------------");

        // Dừng mô phỏng
        #200 $finish;
    end

endmodule

RTL_EYE/tb_spi_waveform.vcd
$date
	Sat Apr 25 15:27:26 2026
$end
$version
	QuestaSim Version 10.7c
$end
$timescale
	1ps
$end

$scope module tb_spi_slave_debug $end
$var reg 1 ! clk $end
$var reg 1 " rst_n $end
$var reg 1 # spi_cs $end
$var reg 1 $ spi_clk $end
$var reg 1 % spi_mosi $end
$var wire 1 & led_done $end
$var integer 32 ' i $end

$scope task send_spi_byte $end
$var reg 8 ( data [7:0] $end
$var integer 32 ) bit_idx $end
$upscope $end

$scope module uut $end
$var parameter 32 * TOTAL_BYTES $end
$var wire 1 + clk $end
$var wire 1 , rst_n $end
$var wire 1 - spi_cs $end
$var wire 1 . spi_clk $end
$var wire 1 / spi_mosi $end
$var wire 1 & led_done $end
$var reg 3 0 cs_sync [2:0] $end
$var reg 3 1 sck_sync [2:0] $end
$var reg 2 2 mosi_sync [1:0] $end
$var wire 1 3 cs_active $end
$var wire 1 4 cs_fall $end
$var wire 1 5 cs_rise $end
$var wire 1 6 sck_rise $end
$var reg 3 7 bit_cnt [2:0] $end
$var reg 7 8 byte_cnt [6:0] $end
$var reg 1 9 led_reg $end
$upscope $end
$upscope $end
$enddefinitions $end
#0
$dumpvars
0!
0"
1#
0$
0%
b111 0
b0 1
b0 2
b0 7
b0 8
09
bx (
b1001000 *
bx '
bx )
0&
03
04
05
06
0/
0.
1-
0,
0+
$end
#10000
1!
1+
#20000
0!
0+
#30000
1!
1+
#40000
0!
0+
#50000
1!
1+
#60000
0!
0+
#70000
1!
1+
#80000
0!
0+
#90000
1!
1+
#100000
1"
0!
1,
0+
#110000
1!
1+
#120000
0!
0+
#130000
1!
1+
#140000
0!
0+
#150000
1!
1+
#160000
0!
0+
#170000
1!
1+
#180000
0!
0+
#190000
1!
1+
#200000
0#
0!
0-
0+
#210000
1!
1+
b110 0
#220000
0!
0+
#230000
1!
1+
b100 0
13
14
#240000
0!
0+
#250000
1!
1+
b0 0
04
#260000
0!
0+
#270000
1!
1+
#280000
0!
0+
#290000
1!
1+
#300000
b0 '
b0 (
b111 )
0!
0+
#310000
1!
1+
#320000
0!
0+
#330000
1!
1+
#340000
1$
0!
1.
0+
#350000
1!
1+
b1 1
#360000
0!
0+
#370000
1!
1+
b11 1
16
#380000
0$
0!
0.
0+
#390000
1!
1+
b1 7
b110 1
06
#400000
0!
0+
#410000
1!
1+
b100 1
#420000
b110 )
0!
0+
#430000
1!
1+
b0 1
#440000
0!
0+
#450000
1!
1+
#460000
1$
0!
1.
0+
#470000
1!
1+
b1 1
#480000
0!
0+
#490000
1!
1+
b11 1
16
#500000
0$
0!
0.
0+
#510000
1!
1+
b10 7
b110 1
06
#520000
0!
0+
#530000
1!
1+
b100 1
#540000
b101 )
0!
0+
#550000
1!
1+
b0 1
#560000
0!
0+
#570000
1!
1+
#580000
1$
0!
1.
0+
#590000
1!
1+
b1 1
#600000
0!
0+
#610000
1!
1+
b11 1
16
#620000
0$
0!
0.
0+
#630000
1!
1+
b11 7
b110 1
06
#640000
0!
0+
#650000
1!
1+
b100 1
#660000
b100 )
0!
0+
#670000
1!
1+
b0 1
#680000
0!
0+
#690000
1!
1+
#700000
1$
0!
1.
0+
#710000
1!
1+
b1 1
#720000
0!
0+
#730000
1!
1+
b11 1
16
#740000
0$
0!
0.
0+
#750000
1!
1+
b100 7
b110 1
06
#760000
0!
0+
#770000
1!
1+
b100 1
#780000
b11 )
0!
0+
#790000
1!
1+
b0 1
#800000
0!
0+
#810000
1!
1+
#820000
1$
0!
1.
0+
#830000
1!
1+
b1 1
#840000
0!
0+
#850000
1!
1+
b11 1
16
#860000
0$
0!
0.
0+
#870000
1!
1+
b101 7
b110 1
06
#880000
0!
0+
#890000
1!
1+
b100 1
#900000
b10 )
0!
0+
#910000
1!
1+
b0 1
#920000
0!
0+
#930000
1!
1+
#940000
1$
0!
1.
0+
#950000
1!
1+
b1 1
#960000
0!
0+
#970000
1!
1+
b11 1
16
#980000
0$
0!
0.
0+
#990000
1!
1+
b110 7
b110 1
06
#1000000
0!
0+
#1010000
1!
1+
b100 1
#1020000
b1 )
0!
0+
#1030000
1!
1+
b0 1
#1040000
0!
0+
#1050000
1!
1+
#1060000
1$
0!
1.
0+
#1070000
1!
1+
b1 1
#1080000
0!
0+
#1090000
1!
1+
b11 1
16
#1100000
0$
0!
0.
0+
#1110000
1!
1+
b111 7
b110 1
06
#1120000
0!
0+
#1130000
1!
1+
b100 1
#1140000
b0 )
0!
0+
#1150000
1!
1+
b0 1
#1160000
0!
0+
#1170000
1!
1+
#1180000
1$
0!
1.
0+
#1190000
1!
1+
b1 1
#1200000
0!
0+
#1210000
1!
1+
b11 1
16
#1220000
0$
0!
0.
0+
#1230000
1!
1+
b0 7
b1 8
b110 1
06
#1240000
0!
0+
#1250000
1!
1+
b100 1
#1260000
b11111111111111111111111111111111 )
b1 '
b1 (
b111 )
0!
0+
#1270000
1!
1+
b0 1
#1280000
0!
0+
#1290000
1!
1+
#1300000
1$
0!
1.
0+
#1310000
1!
1+
b1 1
#1320000
0!
0+
#1330000
1!
1+
b11 1
16
#1340000
0$
0!
0.
0+
#1350000
1!
1+
b1 7
b110 1
06
#1360000
0!
0+
#1370000
1!
1+
b100 1
#1380000
b110 )
0!
0+
#1390000
1!
1+
b0 1
#1400000
0!
0+
#1410000
1!
1+
#1420000
1$
0!
1.
0+
#1430000
1!
1+
b1 1
#1440000
0!
0+
#1450000
1!
1+
b11 1
16
#1460000
0$
0!
0.
0+
#1470000
1!
1+
b10 7
b110 1
06
#1480000
0!
0+
#1490000
1!
1+
b100 1
#1500000
b101 )
0!
0+
#1510000
1!
1+
b0 1
#1520000
0!
0+
#1530000
1!
1+
#1540000
1$
0!
1.
0+
#1550000
1!
1+
b1 1
#1560000
0!
0+
#1570000
1!
1+
b11 1
16
#1580000
0$
0!
0.
0+
#1590000
1!
1+
b11 7
b110 1
06
#1600000
0!
0+
#1610000
1!
1+
b100 1
#1620000
b100 )
0!
0+
#1630000
1!
1+
b0 1
#1640000
0!
0+
#1650000
1!
1+
#1660000
1$
0!
1.
0+
#1670000
1!
1+
b1 1
#1680000
0!
0+
#1690000
1!
1+
b11 1
16
#1700000
0$
0!
0.
0+
#1710000
1!
1+
b100 7
b110 1
06
#1720000
0!
0+
#1730000
1!
1+
b100 1
#1740000
b11 )
0!
0+
#1750000
1!
1+
b0 1
#1760000
0!
0+
#1770000
1!
1+
#1780000
1$
0!
1.
0+
#1790000
1!
1+
b1 1
#1800000
0!
0+
#1810000
1!
1+
b11 1
16
#1820000
0$
0!
0.
0+
#1830000
1!
1+
b101 7
b110 1
06
#1840000
0!
0+
#1850000
1!
1+
b100 1
#1860000
b10 )
0!
0+
#1870000
1!
1+
b0 1
#1880000
0!
0+
#1890000
1!
1+
#1900000
1$
0!
1.
0+
#1910000
1!
1+
b1 1
#1920000
0!
0+
#1930000
1!
1+
b11 1
16
#1940000
0$
0!
0.
0+
#1950000
1!
1+
b110 7
b110 1
06
#1960000
0!
0+
#1970000
1!
1+
b100 1
#1980000
b1 )
0!
0+
#1990000
1!
1+
b0 1
#2000000
0!
0+
#2010000
1!
1+
#2020000
1$
0!
1.
0+
#2030000
1!
1+
b1 1
#2040000
0!
0+
#2050000
1!
1+
b11 1
16
#2060000
0$
0!
0.
0+
#2070000
1!
1+
b111 7
b110 1
06
#2080000
0!
0+
#2090000
1!
1+
b100 1
#2100000
b0 )
1%
0!
1/
0+
#2110000
1!
1+
b0 1
b1 2
#2120000
0!
0+
#2130000
1!
1+
b11 2
#2140000
1$
0!
1.
0+
#2150000
1!
1+
b1 1
#2160000
0!
0+
#2170000
1!
1+
b11 1
16
#2180000
0$
0!
0.
0+
#2190000
1!
1+
b0 7
b10 8
b110 1
06
#2200000
0!
0+
#2210000
1!
1+
b100 1
#2220000
b11111111111111111111111111111111 )
b10 '
b10 (
b111 )
0%
0!
0/
0+
#2230000
1!
1+
b0 1
b10 2
#2240000
0!
0+
#2250000
1!
1+
b0 2
#2260000
1$
0!
1.
0+
#2270000
1!
1+
b1 1
#2280000
0!
0+
#2290000
1!
1+
b11 1
16
#2300000
0$
0!
0.
0+
#2310000
1!
1+
b1 7
b110 1
06
#2320000
0!
0+
#2330000
1!
1+
b100 1
#2340000
b110 )
0!
0+
#2350000
1!
1+
b0 1
#2360000
0!
0+
#2370000
1!
1+
#2380000
1$
0!
1.
0+
#2390000
1!
1+
b1 1
#2400000
0!
0+
#2410000
1!
1+
b11 1
16
#2420000
0$
0!
0.
0+
#2430000
1!
1+
b10 7
b110 1
06
#2440000
0!
0+
#2450000
1!
1+
b100 1
#2460000
b101 )
0!
0+
#2470000
1!
1+
b0 1
#2480000
0!
0+
#2490000
1!
1+
#2500000
1$
0!
1.
0+
#2510000
1!
1+
b1 1
#2520000
0!
0+
#2530000
1!
1+
b11 1
16
#2540000
0$
0!
0.
0+
#2550000
1!
1+
b11 7
b110 1
06
#2560000
0!
0+
#2570000
1!
1+
b100 1
#2580000
b100 )
0!
0+
#2590000
1!
1+
b0 1
#2600000
0!
0+
#2610000
1!
1+
#2620000
1$
0!
1.
0+
#2630000
1!
1+
b1 1
#2640000
0!
0+
#2650000
1!
1+
b11 1
16
#2660000
0$
0!
0.
0+
#2670000
1!
1+
b100 7
b110 1
06
#2680000
0!
0+
#2690000
1!
1+
b100 1
#2700000
b11 )
0!
0+
#2710000
1!
1+
b0 1
#2720000
0!
0+
#2730000
1!
1+
#2740000
1$
0!
1.
0+
#2750000
1!
1+
b1 1
#2760000
0!
0+
#2770000
1!
1+
b11 1
16
#2780000
0$
0!
0.
0+
#2790000
1!
1+
b101 7
b110 1
06
#2800000
0!
0+
#2810000
1!
1+
b100 1
#2820000
b10 )
0!
0+
#2830000
1!
1+
b0 1
#2840000
0!
0+
#2850000
1!
1+
#2860000
1$
0!
1.
0+
#2870000
1!
1+
b1 1
#2880000
0!
0+
#2890000
1!
1+
b11 1
16
#2900000
0$
0!
0.
0+
#2910000
1!
1+
b110 7
b110 1
06
#2920000
0!
0+
#2930000
1!
1+
b100 1
#2940000
b1 )
1%
0!
1/
0+
#2950000
1!
1+
b0 1
b1 2
#2960000
0!
0+
#2970000
1!
1+
b11 2
#2980000
1$
0!
1.
0+
#2990000
1!
1+
b1 1
#3000000
0!
0+
#3010000
1!
1+
b11 1
16
#3020000
0$
0!
0.
0+
#3030000
1!
1+
b111 7
b110 1
06
#3040000
0!
0+
#3050000
1!
1+
b100 1
#3060000
b0 )
0%
0!
0/
0+
#3070000
1!
1+
b0 1
b10 2
#3080000
0!
0+
#3090000
1!
1+
b0 2
#3100000
1$
0!
1.
0+
#3110000
1!
1+
b1 1
#3120000
0!
0+
#3130000
1!
1+
b11 1
16
#3140000
0$
0!
0.
0+
#3150000
1!
1+
b0 7
b11 8
b110 1
06
#3160000
0!
0+
#3170000
1!
1+
b100 1
#3180000
b11111111111111111111111111111111 )
b11 '
b11 (
b111 )
0!
0+
#3190000
1!
1+
b0 1
#3200000
0!
0+
#3210000
1!
1+
#3220000
1$
0!
1.
0+
#3230000
1!
1+
b1 1
#3240000
0!
0+
#3250000
1!
1+
b11 1
16
#3260000
0$
0!
0.
0+
#3270000
1!
1+
b1 7
b110 1
06
#3280000
0!
0+
#3290000
1!
1+
b100 1
#3300000
b110 )
0!
0+
#3310000
1!
1+
b0 1
#3320000
0!
0+
#3330000
1!
1+
#3340000
1$
0!
1.
0+
#3350000
1!
1+
b1 1
#3360000
0!
0+
#3370000
1!
1+
b11 1
16
#3380000
0$
0!
0.
0+
#3390000
1!
1+
b10 7
b110 1
06
#3400000
0!
0+
#3410000
1!
1+
b100 1
#3420000
b101 )
0!
0+
#3430000
1!
1+
b0 1
#3440000
0!
0+
#3450000
1!
1+
#3460000
1$
0!
1.
0+
#3470000
1!
1+
b1 1
#3480000
0!
0+
#3490000
1!
1+
b11 1
16
#3500000
0$
0!
0.
0+
#3510000
1!
1+
b11 7
b110 1
06
#3520000
0!
0+
#3530000
1!
1+
b100 1
#3540000
b100 )
0!
0+
#3550000
1!
1+
b0 1
#3560000
0!
0+
#3570000
1!
1+
#3580000
1$
0!
1.
0+
#3590000
1!
1+
b1 1
#3600000
0!
0+
#3610000
1!
1+
b11 1
16
#3620000
0$
0!
0.
0+
#3630000
1!
1+
b100 7
b110 1
06
#3640000
0!
0+
#3650000
1!
1+
b100 1
#3660000
b11 )
0!
0+
#3670000
1!
1+
b0 1
#3680000
0!
0+
#3690000
1!
1+
#3700000
1$
0!
1.
0+
#3710000
1!
1+
b1 1
#3720000
0!
0+
#3730000
1!
1+
b11 1
16
#3740000
0$
0!
0.
0+
#3750000
1!
1+
b101 7
b110 1
06
#3760000
0!
0+
#3770000
1!
1+
b100 1
#3780000
b10 )
0!
0+
#3790000
1!
1+
b0 1
#3800000
0!
0+
#3810000
1!
1+
#3820000
1$
0!
1.
0+
#3830000
1!
1+
b1 1
#3840000
0!
0+
#3850000
1!
1+
b11 1
16
#3860000
0$
0!
0.
0+
#3870000
1!
1+
b110 7
b110 1
06
#3880000
0!
0+
#3890000
1!
1+
b100 1
#3900000
b1 )
1%
0!
1/
0+
#3910000
1!
1+
b0 1
b1 2
#3920000
0!
0+
#3930000
1!
1+
b11 2
#3940000
1$
0!
1.
0+
#3950000
1!
1+
b1 1
#3960000
0!
0+
#3970000
1!
1+
b11 1
16
#3980000
0$
0!
0.
0+
#3990000
1!
1+
b111 7
b110 1
06
#4000000
0!
0+
#4010000
1!
1+
b100 1
#4020000
b0 )
0!
0+
#4030000
1!
1+
b0 1
#4040000
0!
0+
#4050000
1!
1+
#4060000
1$
0!
1.
0+
#4070000
1!
1+
b1 1
#4080000
0!
0+
#4090000
1!
1+
b11 1
16
#4100000
0$
0!
0.
0+
#4110000
1!
1+
b0 7
b100 8
b110 1
06
#4120000
0!
0+
#4130000
1!
1+
b100 1
#4140000
b11111111111111111111111111111111 )
b100 '
b100 (
b111 )
0%
0!
0/
0+
#4150000
1!
1+
b0 1
b10 2
#4160000
0!
0+
#4170000
1!
1+
b0 2
#4180000
1$
0!
1.
0+
#4190000
1!
1+
b1 1
#4200000
0!
0+
#4210000
1!
1+
b11 1
16
#4220000
0$
0!
0.
0+
#4230000
1!
1+
b1 7
b110 1
06
#4240000
0!
0+
#4250000
1!
1+
b100 1
#4260000
b110 )
0!
0+
#4270000
1!
1+
b0 1
#4280000
0!
0+
#4290000
1!
1+
#4300000
1$
0!
1.
0+
#4310000
1!
1+
b1 1
#4320000
0!
0+
#4330000
1!
1+
b11 1
16
#4340000
0$
0!
0.
0+
#4350000
1!
1+
b10 7
b110 1
06
#4360000
0!
0+
#4370000
1!
1+
b100 1
#4380000
b101 )
0!
0+
#4390000
1!
1+
b0 1
#4400000
0!
0+
#4410000
1!
1+
#4420000
1$
0!
1.
0+
#4430000
1!
1+
b1 1
#4440000
0!
0+
#4450000
1!
1+
b11 1
16
#4460000
0$
0!
0.
0+
#4470000
1!
1+
b11 7
b110 1
06
#4480000
0!
0+
#4490000
1!
1+
b100 1
#4500000
b100 )
0!
0+
#4510000
1!
1+
b0 1
#4520000
0!
0+
#4530000
1!
1+
#4540000
1$
0!
1.
0+
#4550000
1!
1+
b1 1
#4560000
0!
0+
#4570000
1!
1+
b11 1
16
#4580000
0$
0!
0.
0+
#4590000
1!
1+
b100 7
b110 1
06
#4600000
0!
0+
#4610000
1!
1+
b100 1
#4620000
b11 )
0!
0+
#4630000
1!
1+
b0 1
#4640000
0!
0+
#4650000
1!
1+
#4660000
1$
0!
1.
0+
#4670000
1!
1+
b1 1
#4680000
0!
0+
#4690000
1!
1+
b11 1
16
#4700000
0$
0!
0.
0+
#4710000
1!
1+
b101 7
b110 1
06
#4720000
0!
0+
#4730000
1!
1+
b100 1
#4740000
b10 )
1%
0!
1/
0+
#4750000
1!
1+
b0 1
b1 2
#4760000
0!
0+
#4770000
1!
1+
b11 2
#4780000
1$
0!
1.
0+
#4790000
1!
1+
b1 1
#4800000
0!
0+
#4810000
1!
1+
b11 1
16
#4820000
0$
0!
0.
0+
#4830000
1!
1+
b110 7
b110 1
06
#4840000
0!
0+
#4850000
1!
1+
b100 1
#4860000
b1 )
0%
0!
0/
0+
#4870000
1!
1+
b0 1
b10 2
#4880000
0!
0+
#4890000
1!
1+
b0 2
#4900000
1$
0!
1.
0+
#4910000
1!
1+
b1 1
#4920000
0!
0+
#4930000
1!
1+
b11 1
16
#4940000
0$
0!
0.
0+
#4950000
1!
1+
b111 7
b110 1
06
#4960000
0!
0+
#4970000
1!
1+
b100 1
#4980000
b0 )
0!
0+
#4990000
1!
1+
b0 1
#5000000
0!
0+
#5010000
1!
1+
#5020000
1$
0!
1.
0+
#5030000
1!
1+
b1 1
#5040000
0!
0+
#5050000
1!
1+
b11 1
16
#5060000
0$
0!
0.
0+
#5070000
1!
1+
b0 7
b101 8
b110 1
06
#5080000
0!
0+
#5090000
1!
1+
b100 1
#5100000
b11111111111111111111111111111111 )
b101 '
b101 (
b111 )
0!
0+
#5110000
1!
1+
b0 1
#5120000
0!
0+
#5130000
1!
1+
#5140000
1$
0!
1.
0+
#5150000
1!
1+
b1 1
#5160000
0!
0+
#5170000
1!
1+
b11 1
16
#5180000
0$
0!
0.
0+
#5190000
1!
1+
b1 7
b110 1
06
#5200000
0!
0+
#5210000
1!
1+
b100 1
#5220000
b110 )
0!
0+
#5230000
1!
1+
b0 1
#5240000
0!
0+
#5250000
1!
1+
#5260000
1$
0!
1.
0+
#5270000
1!
1+
b1 1
#5280000
0!
0+
#5290000
1!
1+
b11 1
16
#5300000
0$
0!
0.
0+
#5310000
1!
1+
b10 7
b110 1
06
#5320000
0!
0+
#5330000
1!
1+
b100 1
#5340000
b101 )
0!
0+
#5350000
1!
1+
b0 1
#5360000
0!
0+
#5370000
1!
1+
#5380000
1$
0!
1.
0+
#5390000
1!
1+
b1 1
#5400000
0!
0+
#5410000
1!
1+
b11 1
16
#5420000
0$
0!
0.
0+
#5430000
1!
1+
b11 7
b110 1
06
#5440000
0!
0+
#5450000
1!
1+
b100 1
#5460000
b100 )
0!
0+
#5470000
1!
1+
b0 1
#5480000
0!
0+
#5490000
1!
1+
#5500000
1$
0!
1.
0+
#5510000
1!
1+
b1 1
#5520000
0!
0+
#5530000
1!
1+
b11 1
16
#5540000
0$
0!
0.
0+
#5550000
1!
1+
b100 7
b110 1
06
#5560000
0!
0+
#5570000
1!
1+
b100 1
#5580000
b11 )
0!
0+
#5590000
1!
1+
b0 1
#5600000
0!
0+
#5610000
1!
1+
#5620000
1$
0!
1.
0+
#5630000
1!
1+
b1 1
#5640000
0!
0+
#5650000
1!
1+
b11 1
16
#5660000
0$
0!
0.
0+
#5670000
1!
1+
b101 7
b110 1
06
#5680000
0!
0+
#5690000
1!
1+
b100 1
#5700000
b10 )
1%
0!
1/
0+
#5710000
1!
1+
b0 1
b1 2
#5720000
0!
0+
#5730000
1!
1+
b11 2
#5740000
1$
0!
1.
0+
#5750000
1!
1+
b1 1
#5760000
0!
0+
#5770000
1!
1+
b11 1
16
#5780000
0$
0!
0.
0+
#5790000
1!
1+
b110 7
b110 1
06
#5800000
0!
0+
#5810000
1!
1+
b100 1
#5820000
b1 )
0%
0!
0/
0+
#5830000
1!
1+
b0 1
b10 2
#5840000
0!
0+
#5850000
1!
1+
b0 2
#5860000
1$
0!
1.
0+
#5870000
1!
1+
b1 1
#5880000
0!
0+
#5890000
1!
1+
b11 1
16
#5900000
0$
0!
0.
0+
#5910000
1!
1+
b111 7
b110 1
06
#5920000
0!
0+
#5930000
1!
1+
b100 1
#5940000
b0 )
1%
0!
1/
0+
#5950000
1!
1+
b0 1
b1 2
#5960000
0!
0+
#5970000
1!
1+
b11 2
#5980000
1$
0!
1.
0+
#5990000
1!
1+
b1 1
#6000000
0!
0+
#6010000
1!
1+
b11 1
16
#6020000
0$
0!
0.
0+
#6030000
1!
1+
b0 7
b110 8
b110 1
06
#6040000
0!
0+
#6050000
1!
1+
b100 1
#6060000
b11111111111111111111111111111111 )
b110 '
b110 (
b111 )
0%
0!
0/
0+
#6070000
1!
1+
b0 1
b10 2
#6080000
0!
0+
#6090000
1!
1+
b0 2
#6100000
1$
0!
1.
0+
#6110000
1!
1+
b1 1
#6120000
0!
0+
#6130000
1!
1+
b11 1
16
#6140000
0$
0!
0.
0+
#6150000
1!
1+
b1 7
b110 1
06
#6160000
0!
0+
#6170000
1!
1+
b100 1
#6180000
b110 )
0!
0+
#6190000
1!
1+
b0 1
#6200000
0!
0+
#6210000
1!
1+
#6220000
1$
0!
1.
0+
#6230000
1!
1+
b1 1
#6240000
0!
0+
#6250000
1!
1+
b11 1
16
#6260000
0$
0!
0.
0+
#6270000
1!
1+
b10 7
b110 1
06
#6280000
0!
0+
#6290000
1!
1+
b100 1
#6300000
b101 )
0!
0+
#6310000
1!
1+
b0 1
#6320000
0!
0+
#6330000
1!
1+
#6340000
1$
0!
1.
0+
#6350000
1!
1+
b1 1
#6360000
0!
0+
#6370000
1!
1+
b11 1
16
#6380000
0$
0!
0.
0+
#6390000
1!
1+
b11 7
b110 1
06
#6400000
0!
0+
#6410000
1!
1+
b100 1
#6420000
b100 )
0!
0+
#6430000
1!
1+
b0 1
#6440000
0!
0+
#6450000
1!
1+
#6460000
1$
0!
1.
0+
#6470000
1!
1+
b1 1
#6480000
0!
0+
#6490000
1!
1+
b11 1
16
#6500000
0$
0!
0.
0+
#6510000
1!
1+
b100 7
b110 1
06
#6520000
0!
0+
#6530000
1!
1+
b100 1
#6540000
b11 )
0!
0+
#6550000
1!
1+
b0 1
#6560000
0!
0+
#6570000
1!
1+
#6580000
1$
0!
1.
0+
#6590000
1!
1+
b1 1
#6600000
0!
0+
#6610000
1!
1+
b11 1
16
#6620000
0$
0!
0.
0+
#6630000
1!
1+
b101 7
b110 1
06
#6640000
0!
0+
#6650000
1!
1+
b100 1
#6660000
b10 )
1%
0!
1/
0+
#6670000
1!
1+
b0 1
b1 2
#6680000
0!
0+
#6690000
1!
1+
b11 2
#6700000
1$
0!
1.
0+
#6710000
1!
1+
b1 1
#6720000
0!
0+
#6730000
1!
1+
b11 1
16
#6740000
0$
0!
0.
0+
#6750000
1!
1+
b110 7
b110 1
06
#6760000
0!
0+
#6770000
1!
1+
b100 1
#6780000
b1 )
0!
0+
#6790000
1!
1+
b0 1
#6800000
0!
0+
#6810000
1!
1+
#6820000
1$
0!
1.
0+
#6830000
1!
1+
b1 1
#6840000
0!
0+
#6850000
1!
1+
b11 1
16
#6860000
0$
0!
0.
0+
#6870000
1!
1+
b111 7
b110 1
06
#6880000
0!
0+
#6890000
1!
1+
b100 1
#6900000
b0 )
0%
0!
0/
0+
#6910000
1!
1+
b0 1
b10 2
#6920000
0!
0+
#6930000
1!
1+
b0 2
#6940000
1$
0!
1.
0+
#6950000
1!
1+
b1 1
#6960000
0!
0+
#6970000
1!
1+
b11 1
16
#6980000
0$
0!
0.
0+
#6990000
1!
1+
b0 7
b111 8
b110 1
06
#7000000
0!
0+
#7010000
1!
1+
b100 1
#7020000
b11111111111111111111111111111111 )
b111 '
b111 (
b111 )
0!
0+
#7030000
1!
1+
b0 1
#7040000
0!
0+
#7050000
1!
1+
#7060000
1$
0!
1.
0+
#7070000
1!
1+
b1 1
